LICENSE
MANIFEST.in
README.rst
setup.py
debug_toolbar_line_profiler/__init__.py
debug_toolbar_line_profiler/panel.py
debug_toolbar_line_profiler/signals.py
debug_toolbar_line_profiler/static/debug_toolbar_line_profiler/js/toolbar.profiling.js
debug_toolbar_line_profiler/templates/debug_toolbar_line_profiler/panels/profiling.html
django_debug_toolbar_line_profiler.egg-info/PKG-INFO
django_debug_toolbar_line_profiler.egg-info/SOURCES.txt
django_debug_toolbar_line_profiler.egg-info/dependency_links.txt
django_debug_toolbar_line_profiler.egg-info/not-zip-safe
django_debug_toolbar_line_profiler.egg-info/pbr.json
django_debug_toolbar_line_profiler.egg-info/requires.txt
django_debug_toolbar_line_profiler.egg-info/top_level.txt