Metadata-Version: 1.1
Name: django-debug-toolbar-line-profiler
Version: 0.5.0
Summary: A panel for django-debug-toolbar that integrates information from line_profiler
Home-page: https://github.com/dmclain/django-debug-toolbar-line-profiler
Author: Dave McLain
Author-email: dmclain@gmail.com
License: BSD
Download-URL: https://pypi.python.org/pypi/django-debug-toolbar-line-profiler
Platform: UNKNOWN
Classifier: Development Status :: 4 - Beta
Classifier: Environment :: Web Environment
Classifier: Framework :: Django
Classifier: Intended Audience :: Developers
Classifier: License :: OSI Approved :: BSD License
Classifier: Operating System :: OS Independent
Classifier: Programming Language :: Python
Classifier: Programming Language :: Python :: 2
Classifier: Programming Language :: Python :: 2.6
Classifier: Programming Language :: Python :: 2.7
Classifier: Programming Language :: Python :: 3
Classifier: Topic :: Software Development :: Libraries :: Python Modules
